passwdqc.cpython-39.so
passwdqc.libs/libpasswdqc-ce4c1821.so.1
passwdqc-0.0.1.dist-info/RECORD
passwdqc-0.0.1.dist-info/top_level.txt
passwdqc-0.0.1.dist-info/WHEEL
passwdqc-0.0.1.dist-info/METADATA
passwdqc-0.0.1.dist-info/LICENSE
