Metadata-Version: 2.1
Name: passwdqc
Version: 0.0.1
Summary: PasswdQC python wrapper
Home-page: https://sr.ht/~frbrgeorge/PasswdqcPython/
Author: Fr. Br. George
Author-email: george@altlinux.org
License: UNKNOWN
Platform: UNKNOWN
Classifier: Programming Language :: C
Classifier: License :: OSI Approved :: BSD License
Classifier: Operating System :: POSIX :: Linux
